manifestare/__init__.py
manifestare/core/DataFrameManifesto.py
manifestare/core/PandasDataFrameManifesto.py
manifestare/core/SparkDataFrameManifesto.py
manifestare/core/__init__.py
test/core/__init__.py
test/core/test_DataFrameManifesto.py
test/core/test_PandasDataFrameManifesto.py
test/core/test_SparkDataFrameManifesto.py
test/testbuilders/PandasDataFrameTestBuilder.py
test/testbuilders/SparkDataFrameTestBuilder.py
test/testbuilders/__init__.py
manifestare-0.0.1.dist-info/LICENSE
manifestare-0.0.1.dist-info/METADATA
manifestare-0.0.1.dist-info/WHEEL
manifestare-0.0.1.dist-info/top_level.txt
manifestare-0.0.1.dist-info/RECORD
